plone.tiles-3.0.3-py3.13-nspkg.pth
plone/tiles/__init__.py
plone/tiles/absoluteurl.py
plone/tiles/configure.zcml
plone/tiles/data.py
plone/tiles/data.rst
plone/tiles/directives.py
plone/tiles/directives.rst
plone/tiles/esi.py
plone/tiles/esi.rst
plone/tiles/fieldtypeconverters.py
plone/tiles/interfaces.py
plone/tiles/meta.py
plone/tiles/meta.zcml
plone/tiles/test.pt
plone/tiles/testing.py
plone/tiles/tile.py
plone/tiles/tiles.rst
plone/tiles/type.py
plone/tiles/tests/__init__.py
plone/tiles/tests/test_data.py
plone/tiles/tests/test_doctests.py
plone_tiles-3.0.3.dist-info/licenses/LICENSE.GPL
plone_tiles-3.0.3.dist-info/licenses/LICENSE.txt
plone_tiles-3.0.3.dist-info/METADATA
plone_tiles-3.0.3.dist-info/WHEEL
plone_tiles-3.0.3.dist-info/namespace_packages.txt
plone_tiles-3.0.3.dist-info/top_level.txt
plone_tiles-3.0.3.dist-info/RECORD
