Metadata-Version: 2.4
Name: plone.tiles
Version: 3.0.3
Summary: APIs for managing tiles
Home-page: https://github.com/plone/plone.tiles
Author: Martin Aspeli
Author-email: optilude@gmail.com
License: GPL version 2
Keywords: plone tiles
Classifier: Development Status :: 5 - Production/Stable
Classifier: Environment :: Web Environment
Classifier: Framework :: Plone
Classifier: Framework :: Plone :: 6.0
Classifier: Framework :: Plone :: 6.1
Classifier: Framework :: Plone :: 6.2
Classifier: Framework :: Plone :: Core
Classifier: License :: OSI Approved :: GNU General Public License v2 (GPLv2)
Classifier: Programming Language :: Python
Classifier: Programming Language :: Python :: 3.8
Classifier: Programming Language :: Python :: 3.9
Classifier: Programming Language :: Python :: 3.10
Classifier: Programming Language :: Python :: 3.11
Classifier: Programming Language :: Python :: 3.12
Classifier: Programming Language :: Python :: 3.13
Classifier: Topic :: Internet :: WWW/HTTP
Classifier: Topic :: Internet :: WWW/HTTP :: Dynamic Content
Classifier: Topic :: Software Development :: Libraries :: Python Modules
Requires-Python: >=3.8
License-File: LICENSE.GPL
License-File: LICENSE.txt
Requires-Dist: plone.subrequest
Requires-Dist: setuptools
Requires-Dist: zope.annotation
Requires-Dist: zope.component
Requires-Dist: zope.configuration
Requires-Dist: zope.interface
Requires-Dist: zope.publisher
Requires-Dist: zope.schema
Requires-Dist: zope.security
Requires-Dist: zope.traversing
Requires-Dist: plone.protect
Requires-Dist: plone.supermodel
Requires-Dist: Zope
Provides-Extra: test
Requires-Dist: plone.testing[z2,zca]; extra == "test"
Requires-Dist: plone.rfc822; extra == "test"
Dynamic: author
Dynamic: author-email
Dynamic: classifier
Dynamic: description
Dynamic: home-page
Dynamic: keywords
Dynamic: license
Dynamic: license-file
Dynamic: provides-extra
Dynamic: requires-dist
Dynamic: requires-python
Dynamic: summary
